{"fname":"lessons.2022.07","stub":true,"vault":{"fsPath":"vault"},"schemaStub":false,"type":"note","updated":1715099308942,"created":1715099308942,"id":"95b3fcv6ki2k1iobp1d9oe5","desc":"","links":[],"anchors":{},"children":["skjb4estsnc9nb6xr110gp4","232eucwh0xdhf7bxkphec1x","ripgcx9dowtlwr3i3kmt1cy","z9aaofhskhaq004b0lyv7no","gyww6vegicgdzcxb0dqswn6","8mb9umm9jf19mruplfo7jzb","1c2gpy7b7nb4zlylila6g43","lrwt5sti2xe2ta2v8vgstiy"],"parent":"1a3zxdx3pq7zzropjj2ohzy","data":{},"title":"07","schema":{"schemaId":"month","moduleId":"lessons"}}
