{"id":"i8QjmjY6rEC8Yg7VcWRY0","title":"2022-01-06","desc":"","updated":1642524676251,"created":1641434589189,"custom":{},"fname":"lessons.2022.01.06","type":"note","vault":{"fsPath":"vault"},"contentHash":"e6addfd379ef6b7672d6ed70ab68efd0","links":[],"anchors":{"class-notes":{"type":"header","text":"Class Notes","value":"class-notes","line":8,"column":0,"depth":2},"倒数-dào-shǔ---countdown-as-in-for-new-years":{"type":"header","text":"倒数 dào shǔ - countdown (as in for New Year's)","value":"倒数-dào-shǔ---countdown-as-in-for-new-years","line":10,"column":0,"depth":3},"vocabulary":{"type":"header","text":"Vocabulary","value":"vocabulary","line":19,"column":0,"depth":2},"画-huà---to-paint":{"type":"header","text":"画 huà - to paint","value":"画-huà---to-paint","line":21,"column":0,"depth":3},"character-breakdown-画":{"type":"header","text":"Character breakdown 画","value":"character-breakdown-画","line":23,"column":0,"depth":4},"护照-hù-zhào---passport":{"type":"header","text":"护照 hù zhào - passport","value":"护照-hù-zhào---passport","line":31,"column":0,"depth":3},"character-breakdown-护":{"type":"header","text":"Character Breakdown 护","value":"character-breakdown-护","line":33,"column":0,"depth":4},"行李箱-xíng-lǐ-xiāng":{"type":"header","text":"行李箱 xíng lǐ xiāng","value":"行李箱-xíng-lǐ-xiāng","line":43,"column":0,"depth":3},"司机-sī-jī---driver":{"type":"header","text":"司机 sī jī - driver","value":"司机-sī-jī---driver","line":49,"column":0,"depth":3},"西-xī---west":{"type":"header","text":"西 xī - west","value":"西-xī---west","line":60,"column":0,"depth":3},"太阳-tài-yáng":{"type":"header","text":"太阳 tài yáng","value":"太阳-tài-yáng","line":74,"column":0,"depth":3},"黑板-blackboard":{"type":"header","text":"黑板 blackboard","value":"黑板-blackboard","line":80,"column":0,"depth":3},"自己-zi-ji":{"type":"header","text":"自己 zi ji","value":"自己-zi-ji","line":82,"column":0,"depth":3}},"children":[],"parent":"tarcarkeqc6xntfenmjuo95","data":{},"schema":{"schemaId":"day","moduleId":"lessons"}}
