{"id":"o8d8k02kith2oykufrapr0o","title":"2022-03-21","desc":"","updated":1647828254016,"created":1647828254016,"custom":{},"fname":"lessons.2022.03.21","type":"note","vault":{"fsPath":"vault"},"contentHash":"af8d0aadf3502e03de9ae057696ab049","links":[{"type":"wiki","from":{"fname":"lessons.2022.03.21","id":"o8d8k02kith2oykufrapr0o","vaultName":"vault"},"value":"lessons.2021.10.25","alias":"HSK3 - Lesson 3","position":{"start":{"line":47,"column":23,"offset":998},"end":{"line":47,"column":77,"offset":1052},"indent":[]},"xvault":false,"sameFile":false,"to":{"fname":"lessons.2021.10.25","anchorHeader":"hsk3---lesson-3"}}],"anchors":{"class-notes":{"type":"header","text":"Class Notes","value":"class-notes","line":8,"column":0,"depth":2},"挂科-guà-kē---failed-slang":{"type":"header","text":"挂科 guà kē - failed (slang)","value":"挂科-guà-kē---failed-slang","line":10,"column":0,"depth":3},"vocabulary":{"type":"header","text":"Vocabulary","value":"vocabulary","line":16,"column":0,"depth":2},"经过-jīng-guò---to-have-passed-by-somewhere-or-something-elapsed":{"type":"header","text":"经过 jīng guò - to have passed by somewhere or something, elapsed.","value":"经过-jīng-guò---to-have-passed-by-somewhere-or-something-elapsed","line":18,"column":0,"depth":3},"碗-wǎn---bowl":{"type":"header","text":"碗 wǎn - bowl","value":"碗-wǎn---bowl","line":22,"column":0,"depth":3},"东-dōng---east":{"type":"header","text":"东 dōng - East","value":"东-dōng---east","line":26,"column":0,"depth":3},"照相机-zhào-xiàng-jī---camera":{"type":"header","text":"照相机 zhào xiàng jī - camera","value":"照相机-zhào-xiàng-jī---camera","line":31,"column":0,"depth":3},"信用卡-xìn-yòng-kǎ---credit-card":{"type":"header","text":"信用卡 xìn yòng kǎ - credit card","value":"信用卡-xìn-yòng-kǎ---credit-card","line":33,"column":0,"depth":3},"成绩-chéng-jì---grades":{"type":"header","text":"成绩 chéng jì - grades","value":"成绩-chéng-jì---grades","line":35,"column":0,"depth":3},"试-shì---try":{"type":"header","text":"试 shì - try","value":"试-shì---try","line":41,"column":0,"depth":3},"关心-guān-xīn---care":{"type":"header","text":"关心 guān xīn - care","value":"关心-guān-xīn---care","line":49,"column":0,"depth":3},"难过-nán-guò---saddened":{"type":"header","text":"难过 nán guò - saddened","value":"难过-nán-guò---saddened","line":55,"column":0,"depth":3},"多么-duō-me---how":{"type":"header","text":"多么？ duō me - how？","value":"多么-duō-me---how","line":59,"column":0,"depth":3}},"children":[],"parent":"wtvznp7aquzqe8uybse0bz4","data":{},"schema":{"schemaId":"day","moduleId":"lessons"}}
