{"id":"VGTsTXhrREuYjcjspAW6g","title":"Grammar","desc":"","updated":1633193152248,"created":1633193152248,"stub":true,"custom":{"stub":true},"fname":"grammar","type":"note","vault":{"fsPath":"vault"},"contentHash":"57a972b037ad276cf4febcfa46d6df72","links":[],"anchors":{},"children":["uwz80q7539koxeiqt6fi7od","BSDMRmLFvrEx0GZmUV572","A1Yo0JG7aZ6I9xZnSJ3lb","c41bldgg330t12ky7bl8wb1","h3rDjZET4YapUrarPum7P","euzfa3ulr5sbmonybk0hgbw","bnpsr50jddi5fob6vo8wu0b"],"parent":"tP0mD90vo9yAk1VHyoVSk","data":{}}
