{"id":"cFNMkvUUDb4YIvJhbej4H","title":"30","vault":{"fsPath":"vault"},"type":"note","desc":"","links":[],"anchors":{"class-notes":{"type":"header","value":"class-notes","line":8,"column":0},"continued-notes-of-le":{"type":"header","value":"continued-notes-of-le","line":10,"column":0},"就":{"type":"header","value":"就","line":24,"column":0},"te-bie":{"type":"header","value":"te-bie","line":32,"column":0},"guo-with-le":{"type":"header","value":"guo-with-le","line":43,"column":0},"he-vs-ye":{"type":"header","value":"he-vs-ye","line":55,"column":0},"vocabulary":{"type":"header","value":"vocabulary","line":69,"column":0}},"fname":"chinese.lessons.2021.09.30","updated":1632973019921,"created":1632964496159,"parent":"jIikjxR81Q6WhnUDAf45q","children":[],"data":{},"contentHash":"bc81598a24245289ed055853b8ab0867","custom":{}}
