{"id":"yUBJXZ0kM0GE3j77QBNlz","title":"2021-10-11","vault":{"fsPath":"vault"},"type":"note","desc":"","links":[],"anchors":{"class-notes":{"type":"header","text":"Class Notes","value":"class-notes","line":8,"column":0},"using-的-at-the-end-of-sentences":{"type":"header","text":"Using 的 at the end of sentences:","value":"using-的-at-the-end-of-sentences","line":10,"column":0},"characters-to-remember":{"type":"header","text":"Characters to Remember","value":"characters-to-remember","line":27,"column":0},"zhōumò---周末-weekend":{"type":"header","text":"Zhōumò - 周末 （weekend）","value":"zhōumò---周末-weekend","line":29,"column":0},"different-uses-of-包":{"type":"header","text":"different uses of 包","value":"different-uses-of-包","line":35,"column":0},"游-yóu":{"type":"header","text":"游 yóu","value":"游-yóu","line":39,"column":0},"vocabulary":{"type":"header","text":"Vocabulary","value":"vocabulary","line":45,"column":0},"hsk3---lesson-1":{"type":"header","text":"HSK3 - Lesson 1","value":"hsk3---lesson-1","line":47,"column":0},"hsk3---lesson-2":{"type":"header","text":"HSK3 - Lesson 2","value":"hsk3---lesson-2","line":64,"column":0},"hsk3---lesson-3":{"type":"header","text":"HSK3 - Lesson 3","value":"hsk3---lesson-3","line":84,"column":0},"prepared-passage":{"type":"header","text":"Prepared Passage","value":"prepared-passage","line":105,"column":0},"original-汉子-attempt":{"type":"header","text":"Original 汉子 Attempt","value":"original-汉子-attempt","line":107,"column":0},"pīnyīn":{"type":"header","text":"pīnyīn","value":"pīnyīn","line":113,"column":0},"english-meaning":{"type":"header","text":"English Meaning","value":"english-meaning","line":119,"column":0},"corrected-passage-from-老师":{"type":"header","text":"Corrected passage from 老师：","value":"corrected-passage-from-老师","line":125,"column":0},"notes":{"type":"header","text":"Notes","value":"notes","line":132,"column":0}},"fname":"lessons.2021.10.11","updated":1633968288417,"created":1633853177910,"parent":"OhkJUYGJAEYFsYQwhjJXs","children":[],"data":{},"contentHash":"d6d4d109cd876d096c3e32731b21f7d1","custom":{},"schema":{"schemaId":"day","moduleId":"lessons"}}
